video_concatenate_mcp/__init__.py
video_concatenate_mcp/main.py
mcpcn_video_concatenate_mcp-0.1.3.dist-info/METADATA
mcpcn_video_concatenate_mcp-0.1.3.dist-info/WHEEL
mcpcn_video_concatenate_mcp-0.1.3.dist-info/entry_points.txt
mcpcn_video_concatenate_mcp-0.1.3.dist-info/RECORD
